{"v":"5.7.8","fr":60,"ip":0,"op":120,"w":1600,"h":1200,"nm":"스쿨북","ddd":0,"assets":[{"id":"comp_0","layers":[{"ddd":0,"ind":1,"ty":4,"nm":"Shape Layer 30","sr":1,"ks":{"o":{"a":0,"k":100,"ix":11},"r":{"a":0,"k":0,"ix":10},"p":{"a":0,"k":[535.75,550.5,0],"ix":2,"l":2},"a":{"a":0,"k":[-264.25,-49.5,0],"ix":1,"l":2},"s":{"a":0,"k":[100,100,100],"ix":6,"l":2}},"ao":0,"shapes":[{"ty":"gr","it":[{"ind":0,"ty":"sh","ix":1,"ks":{"a":0,"k":{"i":[[2,210],[-34,-58],[46,-30],[10,-54],[-96,-8],[-86,90],[0,0],[0,0],[0,17.5],[0,0],[0,0],[-10.407,-11.223],[0,0]],"o":[[-2,-210],[34,58],[-46,30],[-10,54],[96,8],[86,-90],[0,0],[0,0],[0,-17.5],[0,0],[0,0],[12.75,13.75],[0,0]],"v":[[-894,-246],[-632,-290],[-640,-124],[-760,18],[-688,206],[-480,92],[-303.75,-1],[-247,-35],[-227,-70.25],[-227.5,-95.25],[-227,-65.25],[-211,-39.75],[-152.25,-1.75]],"c":false},"ix":2},"nm":"Path 1","mn":"ADBE Vector Shape - Group","hd":false},{"ty":"st","c":{"a":0,"k":[1,1,1,1],"ix":3},"o":{"a":0,"k":100,"ix":4},"w":{"a":0,"k":20,"ix":5},"lc":2,"lj":2,"bm":0,"nm":"Stroke 1","mn":"ADBE Vector Graphic - Stroke","hd":false},{"ty":"tr","p":{"a":0,"k":[0,0],"ix":2},"a":{"a":0,"k":[0,0],"ix":1},"s":{"a":0,"k":[100,100],"ix":3},"r":{"a":0,"k":0,"ix":6},"o":{"a":0,"k":100,"ix":7},"sk":{"a":0,"k":0,"ix":4},"sa":{"a":0,"k":0,"ix":5},"nm":"Transform"}],"nm":"Shape 1","np":3,"cix":2,"bm":0,"ix":1,"mn":"ADBE Vector Group","hd":false},{"ty":"tm","s":{"a":1,"k":[{"i":{"x":[0],"y":[0.988]},"o":{"x":[0.167],"y":[0.167]},"t":10,"s":[0]},{"t":70,"s":[100]}],"ix":1},"e":{"a":1,"k":[{"i":{"x":[0.154],"y":[0.984]},"o":{"x":[0.167],"y":[0.167]},"t":10,"s":[0]},{"t":90,"s":[84.4]}],"ix":2},"o":{"a":0,"k":0,"ix":3},"m":1,"ix":2,"nm":"Trim Paths 1","mn":"ADBE Vector Filter - Trim","hd":false}],"ip":10,"op":130,"st":10,"bm":0},{"ddd":0,"ind":2,"ty":4,"nm":"Shape Layer 29","sr":1,"ks":{"o":{"a":0,"k":100,"ix":11},"r":{"a":0,"k":0,"ix":10},"p":{"a":0,"k":[573.25,665.25,0],"ix":2,"l":2},"a":{"a":0,"k":[-226.75,65.25,0],"ix":1,"l":2},"s":{"a":0,"k":[100,100,100],"ix":6,"l":2}},"ao":0,"shapes":[{"ty":"gr","it":[{"ind":0,"ty":"sh","ix":1,"ks":{"a":0,"k":{"i":[[-46,-6],[-6,66],[82,4],[10,-94],[-52,0],[28,120],[12,126],[0,0],[0,0]],"o":[[46,6],[6,-66],[-82,-4],[-10,94],[52,0],[-28,-120],[-12,-126],[0,0],[0,0]],"v":[[-552,672],[-362,420],[-506,272],[-658,376],[-486,528],[-316,384],[-450,172],[-321.25,65.25],[-132.25,65.25]],"c":false},"ix":2},"nm":"Path 1","mn":"ADBE Vector Shape - Group","hd":false},{"ty":"st","c":{"a":0,"k":[1,1,1,1],"ix":3},"o":{"a":0,"k":100,"ix":4},"w":{"a":0,"k":20,"ix":5},"lc":2,"lj":2,"bm":0,"nm":"Stroke 1","mn":"ADBE Vector Graphic - Stroke","hd":false},{"ty":"tr","p":{"a":0,"k":[0,0],"ix":2},"a":{"a":0,"k":[0,0],"ix":1},"s":{"a":0,"k":[100,100],"ix":3},"r":{"a":0,"k":0,"ix":6},"o":{"a":0,"k":100,"ix":7},"sk":{"a":0,"k":0,"ix":4},"sa":{"a":0,"k":0,"ix":5},"nm":"Transform"}],"nm":"Shape 1","np":3,"cix":2,"bm":0,"ix":1,"mn":"ADBE Vector Group","hd":false},{"ty":"tm","s":{"a":1,"k":[{"i":{"x":[0],"y":[0.977]},"o":{"x":[0.167],"y":[0.167]},"t":10,"s":[0]},{"t":70,"s":[100]}],"ix":1},"e":{"a":1,"k":[{"i":{"x":[0.155],"y":[0.971]},"o":{"x":[0.167],"y":[0.167]},"t":10,"s":[0]},{"t":90,"s":[90.1]}],"ix":2},"o":{"a":0,"k":0,"ix":3},"m":1,"ix":2,"nm":"Trim Paths 1","mn":"ADBE Vector Filter - Trim","hd":false}],"ip":10,"op":130,"st":10,"bm":0},{"ddd":0,"ind":3,"ty":4,"nm":"Shape Layer 28","sr":1,"ks":{"o":{"a":0,"k":100,"ix":11},"r":{"a":0,"k":0,"ix":10},"p":{"a":0,"k":[798.269,536.375,0],"ix":2,"l":2},"a":{"a":0,"k":[-1.731,-63.625,0],"ix":1,"l":2},"s":{"a":0,"k":[100,100,100],"ix":6,"l":2}},"ao":0,"shapes":[{"ty":"gr","it":[{"ind":0,"ty":"sh","ix":1,"ks":{"a":0,"k":{"i":[[-174,2],[-6,-86],[45.629,2.444],[2,-134],[-92,-2],[0,0],[-12.249,0.144],[1.5,-19.25],[2.75,-9.25]],"o":[[174,-2],[6,86],[-45.629,-2.444],[-2,134],[22.085,0.48],[0,0],[21.25,-0.25],[-2.118,27.186],[-2.75,9.25]],"v":[[-170,-702],[36,-540],[-124,-452],[-288,-314],[-158,-106],[-66.5,-102.75],[42,-102.75],[62.5,-84],[56.25,-24.5]],"c":false},"ix":2},"nm":"Path 1","mn":"ADBE Vector Shape - Group","hd":false},{"ty":"st","c":{"a":0,"k":[1,1,1,1],"ix":3},"o":{"a":0,"k":100,"ix":4},"w":{"a":0,"k":20,"ix":5},"lc":2,"lj":2,"bm":0,"nm":"Stroke 1","mn":"ADBE Vector Graphic - Stroke","hd":false},{"ty":"tr","p":{"a":0,"k":[0,0],"ix":2},"a":{"a":0,"k":[0,0],"ix":1},"s":{"a":0,"k":[100,100],"ix":3},"r":{"a":0,"k":0,"ix":6},"o":{"a":0,"k":100,"ix":7},"sk":{"a":0,"k":0,"ix":4},"sa":{"a":0,"k":0,"ix":5},"nm":"Transform"}],"nm":"Shape 1","np":3,"cix":2,"bm":0,"ix":1,"mn":"ADBE Vector Group","hd":false},{"ty":"tm","s":{"a":1,"k":[{"i":{"x":[0],"y":[0.994]},"o":{"x":[0.167],"y":[0.167]},"t":10,"s":[0]},{"t":70,"s":[100]}],"ix":1},"e":{"a":1,"k":[{"i":{"x":[0.158],"y":[0.992]},"o":{"x":[0.167],"y":[0.167]},"t":10,"s":[0]},{"t":90,"s":[84.7]}],"ix":2},"o":{"a":0,"k":0,"ix":3},"m":1,"ix":2,"nm":"Trim Paths 1","mn":"ADBE Vector Filter - Trim","hd":false}],"ip":10,"op":130,"st":10,"bm":0},{"ddd":0,"ind":4,"ty":4,"nm":"Shape Layer 27","sr":1,"ks":{"o":{"a":0,"k":100,"ix":11},"r":{"a":0,"k":0,"ix":10},"p":{"a":0,"k":[795,541.75,0],"ix":2,"l":2},"a":{"a":0,"k":[-5,-58.25,0],"ix":1,"l":2},"s":{"a":0,"k":[100,100,100],"ix":6,"l":2}},"ao":0,"shapes":[{"ty":"gr","it":[{"ind":0,"ty":"sh","ix":1,"ks":{"a":0,"k":{"i":[[26,-50],[-120,-8],[0,68],[72.477,5.575],[-2,-80],[-76,0],[2,-128],[0,0],[0,0]],"o":[[-26,50],[120,8],[0,-68],[-72.477,-5.575],[3.652,146.078],[76,0],[-2,128],[0,0],[0,0]],"v":[[-920,-114],[-512,-256],[-334,-454],[-434,-564],[-584,-476],[-402,-332],[-174,-194],[-69.5,-58.25],[59.5,-58.25]],"c":false},"ix":2},"nm":"Path 1","mn":"ADBE Vector Shape - Group","hd":false},{"ty":"st","c":{"a":0,"k":[1,1,1,1],"ix":3},"o":{"a":0,"k":100,"ix":4},"w":{"a":0,"k":20,"ix":5},"lc":2,"lj":2,"bm":0,"nm":"Stroke 1","mn":"ADBE Vector Graphic - Stroke","hd":false},{"ty":"tr","p":{"a":0,"k":[0,0],"ix":2},"a":{"a":0,"k":[0,0],"ix":1},"s":{"a":0,"k":[100,100],"ix":3},"r":{"a":0,"k":0,"ix":6},"o":{"a":0,"k":100,"ix":7},"sk":{"a":0,"k":0,"ix":4},"sa":{"a":0,"k":0,"ix":5},"nm":"Transform"}],"nm":"Shape 1","np":3,"cix":2,"bm":0,"ix":1,"mn":"ADBE Vector Group","hd":false},{"ty":"tm","s":{"a":1,"k":[{"i":{"x":[0],"y":[1.003]},"o":{"x":[0.167],"y":[0.167]},"t":10,"s":[0]},{"t":70,"s":[100]}],"ix":1},"e":{"a":1,"k":[{"i":{"x":[0.154],"y":[1.003]},"o":{"x":[0.167],"y":[0.167]},"t":10,"s":[0]},{"t":90,"s":[93.7]}],"ix":2},"o":{"a":0,"k":0,"ix":3},"m":1,"ix":2,"nm":"Trim Paths 1","mn":"ADBE Vector Filter - Trim","hd":false}],"ip":10,"op":130,"st":10,"bm":0},{"ddd":0,"ind":5,"ty":4,"nm":"Shape Layer 26","sr":1,"ks":{"o":{"a":0,"k":100,"ix":11},"r":{"a":0,"k":0,"ix":10},"p":{"a":0,"k":[799.875,584.75,0],"ix":2,"l":2},"a":{"a":0,"k":[-0.125,-15.25,0],"ix":1,"l":2},"s":{"a":0,"k":[100,100,100],"ix":6,"l":2}},"ao":0,"shapes":[{"ty":"gr","it":[{"ind":0,"ty":"sh","ix":1,"ks":{"a":0,"k":{"i":[[74,4],[6,192],[-190,-2],[-2,-108],[80.016,-1.212],[-2,214],[0,0],[0,0],[0,0],[0,0]],"o":[[-74,-4],[-6,-192],[77.996,0.821],[2,108],[-80.016,1.212],[2,-214],[0,0],[0,0],[0,0],[0,0]],"v":[[52,688],[-154,516],[68,180],[234,294],[38,428],[-206,180],[-96,-15.25],[95.75,-15.25],[-0.25,-15.25],[-0.25,24.25]],"c":false},"ix":2},"nm":"Path 1","mn":"ADBE Vector Shape - Group","hd":false},{"ty":"st","c":{"a":0,"k":[1,1,1,1],"ix":3},"o":{"a":0,"k":100,"ix":4},"w":{"a":0,"k":20,"ix":5},"lc":2,"lj":2,"bm":0,"nm":"Stroke 1","mn":"ADBE Vector Graphic - Stroke","hd":false},{"ty":"tr","p":{"a":0,"k":[0,0],"ix":2},"a":{"a":0,"k":[0,0],"ix":1},"s":{"a":0,"k":[100,100],"ix":3},"r":{"a":0,"k":0,"ix":6},"o":{"a":0,"k":100,"ix":7},"sk":{"a":0,"k":0,"ix":4},"sa":{"a":0,"k":0,"ix":5},"nm":"Transform"}],"nm":"Shape 1","np":3,"cix":2,"bm":0,"ix":1,"mn":"ADBE Vector Group","hd":false},{"ty":"tm","s":{"a":1,"k":[{"i":{"x":[0],"y":[0.987]},"o":{"x":[0.167],"y":[0.167]},"t":10,"s":[0]},{"t":70,"s":[100]}],"ix":1},"e":{"a":1,"k":[{"i":{"x":[0.154],"y":[0.983]},"o":{"x":[0.167],"y":[0.167]},"t":10,"s":[0]},{"t":90,"s":[85.5]}],"ix":2},"o":{"a":0,"k":0,"ix":3},"m":1,"ix":2,"nm":"Trim Paths 1","mn":"ADBE Vector Filter - Trim","hd":false}],"ip":10,"op":130,"st":10,"bm":0},{"ddd":0,"ind":6,"ty":4,"nm":"Shape Layer 25","sr":1,"ks":{"o":{"a":0,"k":100,"ix":11},"r":{"a":0,"k":0,"ix":10},"p":{"a":0,"k":[802.875,665.67,0],"ix":2,"l":2},"a":{"a":0,"k":[2.875,65.67,0],"ix":1,"l":2},"s":{"a":0,"k":[100,100,100],"ix":6,"l":2}},"ao":0,"shapes":[{"ty":"gr","it":[{"ind":0,"ty":"sh","ix":1,"ks":{"a":0,"k":{"i":[[-155.945,-10.829],[-22,88],[80,0],[-6,-156],[-112,4],[-10,214],[0,0],[-8.246,-0.358],[0,-19],[15,-0.25],[8.996,-0.261],[-0.273,-17.998],[-14.75,0],[0,0]],"o":[[432,30],[18.592,-74.366],[-80,0],[6,156],[112,-4],[10,-214],[0,0],[17.25,0.75],[0,19],[-10.002,0.167],[-17.25,0.5],[0.25,16.5],[10.25,0],[0,0]],"v":[[-854,432],[-380,126],[-554,-72],[-728,136],[-512,424],[-298,226],[-66.5,28.75],[50,28.75],[64.75,48.5],[49.75,66.25],[-48.5,66.25],[-65.5,86.25],[-48.5,102.75],[69.5,102.75]],"c":false},"ix":2},"nm":"Path 1","mn":"ADBE Vector Shape - Group","hd":false},{"ty":"st","c":{"a":0,"k":[1,1,1,1],"ix":3},"o":{"a":0,"k":100,"ix":4},"w":{"a":0,"k":20,"ix":5},"lc":2,"lj":2,"bm":0,"nm":"Stroke 1","mn":"ADBE Vector Graphic - Stroke","hd":false},{"ty":"tr","p":{"a":0,"k":[0,0],"ix":2},"a":{"a":0,"k":[0,0],"ix":1},"s":{"a":0,"k":[100,100],"ix":3},"r":{"a":0,"k":0,"ix":6},"o":{"a":0,"k":100,"ix":7},"sk":{"a":0,"k":0,"ix":4},"sa":{"a":0,"k":0,"ix":5},"nm":"Transform"}],"nm":"Shape 1","np":3,"cix":2,"bm":0,"ix":1,"mn":"ADBE Vector Group","hd":false},{"ty":"tm","s":{"a":1,"k":[{"i":{"x":[0],"y":[1.006]},"o":{"x":[0.167],"y":[0.167]},"t":10,"s":[0]},{"t":70,"s":[100]}],"ix":1},"e":{"a":1,"k":[{"i":{"x":[0.151],"y":[1.009]},"o":{"x":[0.167],"y":[0.167]},"t":10,"s":[0]},{"t":90,"s":[83.6]}],"ix":2},"o":{"a":0,"k":0,"ix":3},"m":1,"ix":2,"nm":"Trim Paths 1","mn":"ADBE Vector Filter - Trim","hd":false}],"ip":10,"op":130,"st":10,"bm":0},{"ddd":0,"ind":7,"ty":4,"nm":"Shape Layer 24","sr":1,"ks":{"o":{"a":0,"k":100,"ix":11},"r":{"a":0,"k":0,"ix":10},"p":{"a":0,"k":[1026.375,528.806,0],"ix":2,"l":2},"a":{"a":0,"k":[226.375,-71.194,0],"ix":1,"l":2},"s":{"a":0,"k":[100,100,100],"ix":6,"l":2}},"ao":0,"shapes":[{"ty":"gr","it":[{"ind":0,"ty":"sh","ix":1,"ks":{"a":0,"k":{"i":[[-220,38],[8,-84],[114,2],[8,66],[-42,8],[-2,-76],[0,0],[0.174,-7.498],[-9,-0.5],[-6.254,0.11],[0.25,14],[0,0]],"o":[[220,-38],[-4.86,51.033],[-114,-2],[-8,-66],[42,-8],[2,76],[0,0],[-0.25,10.75],[6.49,0.361],[14.25,-0.25],[-0.116,-6.499],[0,0]],"v":[[296,-690],[506,-448],[224,-148],[-84,-264],[10,-414],[164,-302],[164,-103],[163.5,-45.25],[177.5,-35.75],[276.75,-35.75],[291.75,-49],[291.75,-102.75]],"c":false},"ix":2},"nm":"Path 1","mn":"ADBE Vector Shape - Group","hd":false},{"ty":"st","c":{"a":0,"k":[1,1,1,1],"ix":3},"o":{"a":0,"k":100,"ix":4},"w":{"a":0,"k":20,"ix":5},"lc":2,"lj":2,"bm":0,"nm":"Stroke 1","mn":"ADBE Vector Graphic - Stroke","hd":false},{"ty":"tr","p":{"a":0,"k":[0,0],"ix":2},"a":{"a":0,"k":[0,0],"ix":1},"s":{"a":0,"k":[100,100],"ix":3},"r":{"a":0,"k":0,"ix":6},"o":{"a":0,"k":100,"ix":7},"sk":{"a":0,"k":0,"ix":4},"sa":{"a":0,"k":0,"ix":5},"nm":"Transform"}],"nm":"Shape 2","np":3,"cix":2,"bm":0,"ix":1,"mn":"ADBE Vector Group","hd":false},{"ty":"gr","it":[{"ty":"st","c":{"a":0,"k":[1,1,1,1],"ix":3},"o":{"a":0,"k":100,"ix":4},"w":{"a":0,"k":20,"ix":5},"lc":1,"lj":1,"ml":4,"bm":0,"nm":"Stroke 1","mn":"ADBE Vector Graphic - Stroke","hd":false},{"ty":"tr","p":{"a":0,"k":[0,0],"ix":2},"a":{"a":0,"k":[0,0],"ix":1},"s":{"a":0,"k":[100,100],"ix":3},"r":{"a":0,"k":0,"ix":6},"o":{"a":0,"k":100,"ix":7},"sk":{"a":0,"k":0,"ix":4},"sa":{"a":0,"k":0,"ix":5},"nm":"Transform"}],"nm":"Shape 1","np":2,"cix":2,"bm":0,"ix":2,"mn":"ADBE Vector Group","hd":false},{"ty":"tm","s":{"a":1,"k":[{"i":{"x":[0],"y":[1]},"o":{"x":[0.167],"y":[0.167]},"t":10,"s":[0]},{"t":70,"s":[100]}],"ix":1},"e":{"a":1,"k":[{"i":{"x":[0.155],"y":[1]},"o":{"x":[0.167],"y":[0.167]},"t":10,"s":[0]},{"t":90,"s":[87.3]}],"ix":2},"o":{"a":0,"k":0,"ix":3},"m":1,"ix":3,"nm":"Trim Paths 1","mn":"ADBE Vector Filter - Trim","hd":false}],"ip":10,"op":130,"st":10,"bm":0},{"ddd":0,"ind":8,"ty":4,"nm":"Shape Layer 23","sr":1,"ks":{"o":{"a":0,"k":100,"ix":11},"r":{"a":0,"k":0,"ix":10},"p":{"a":0,"k":[1026.875,523,0],"ix":2,"l":2},"a":{"a":0,"k":[226.875,-77,0],"ix":1,"l":2},"s":{"a":0,"k":[100,100,100],"ix":6,"l":2}},"ao":0,"shapes":[{"ty":"gr","it":[{"ind":0,"ty":"sh","ix":1,"ks":{"a":0,"k":{"i":[[90,34],[10,-96],[-102,4],[2,-140],[100,4],[-2,116],[96,0],[8,-84],[-88,-4],[0,0],[0,0]],"o":[[-90,-34],[-10,96],[102,-4],[-2,140],[-100,-4],[2,-116],[-96,0],[-8,84],[88,4],[0,0],[0,0]],"v":[[1036,-418],[404,-504],[622,-354],[776,-144],[582,40],[450,-178],[228,-354],[-26,-244],[102,-82],[168.25,-77],[285.5,-77]],"c":false},"ix":2},"nm":"Path 1","mn":"ADBE Vector Shape - Group","hd":false},{"ty":"st","c":{"a":0,"k":[1,1,1,1],"ix":3},"o":{"a":0,"k":100,"ix":4},"w":{"a":0,"k":20,"ix":5},"lc":2,"lj":2,"bm":0,"nm":"Stroke 1","mn":"ADBE Vector Graphic - Stroke","hd":false},{"ty":"tr","p":{"a":0,"k":[0,0],"ix":2},"a":{"a":0,"k":[0,0],"ix":1},"s":{"a":0,"k":[100,100],"ix":3},"r":{"a":0,"k":0,"ix":6},"o":{"a":0,"k":100,"ix":7},"sk":{"a":0,"k":0,"ix":4},"sa":{"a":0,"k":0,"ix":5},"nm":"Transform"}],"nm":"Shape 1","np":3,"cix":2,"bm":0,"ix":1,"mn":"ADBE Vector Group","hd":false},{"ty":"tm","s":{"a":1,"k":[{"i":{"x":[0],"y":[1.004]},"o":{"x":[0.167],"y":[0.167]},"t":10,"s":[0]},{"t":70,"s":[100]}],"ix":1},"e":{"a":1,"k":[{"i":{"x":[0.15],"y":[1.004]},"o":{"x":[0.167],"y":[0.167]},"t":10,"s":[0]},{"t":90,"s":[96]}],"ix":2},"o":{"a":0,"k":0,"ix":3},"m":1,"ix":2,"nm":"Trim Paths 1","mn":"ADBE Vector Filter - Trim","hd":false}],"ip":10,"op":130,"st":10,"bm":0},{"ddd":0,"ind":9,"ty":4,"nm":"Shape Layer 22","sr":1,"ks":{"o":{"a":0,"k":100,"ix":11},"r":{"a":0,"k":0,"ix":10},"p":{"a":0,"k":[1027.875,605,0],"ix":2,"l":2},"a":{"a":0,"k":[227.875,5,0],"ix":1,"l":2},"s":{"a":0,"k":[100,100,100],"ix":6,"l":2}},"ao":0,"shapes":[{"ty":"gr","it":[{"ind":0,"ty":"sh","ix":1,"ks":{"a":0,"k":{"i":[[-24,132],[106,0],[4.23,-114.202],[154,0],[4,150],[0,0],[0,0],[0,0],[0,0]],"o":[[24,-132],[-106,0],[-4.229,114.202],[-154,0],[-4,-150],[0,0],[0,0],[0,0],[0,0]],"v":[[900,326],[668,86],[498,274],[230,440],[18,144],[133.25,4.75],[322.5,4.75],[227,4.75],[227,42.5]],"c":false},"ix":2},"nm":"Path 1","mn":"ADBE Vector Shape - Group","hd":false},{"ty":"st","c":{"a":0,"k":[1,1,1,1],"ix":3},"o":{"a":0,"k":100,"ix":4},"w":{"a":0,"k":20,"ix":5},"lc":2,"lj":2,"bm":0,"nm":"Stroke 1","mn":"ADBE Vector Graphic - Stroke","hd":false},{"ty":"tr","p":{"a":0,"k":[0,0],"ix":2},"a":{"a":0,"k":[0,0],"ix":1},"s":{"a":0,"k":[100,100],"ix":3},"r":{"a":0,"k":0,"ix":6},"o":{"a":0,"k":100,"ix":7},"sk":{"a":0,"k":0,"ix":4},"sa":{"a":0,"k":0,"ix":5},"nm":"Transform"}],"nm":"Shape 1","np":3,"cix":2,"bm":0,"ix":1,"mn":"ADBE Vector Group","hd":false},{"ty":"tm","s":{"a":1,"k":[{"i":{"x":[0],"y":[0.994]},"o":{"x":[0.167],"y":[0.167]},"t":10,"s":[0]},{"t":70,"s":[100]}],"ix":1},"e":{"a":1,"k":[{"i":{"x":[0.155],"y":[0.992]},"o":{"x":[0.167],"y":[0.167]},"t":10,"s":[0]},{"t":90,"s":[83.5]}],"ix":2},"o":{"a":0,"k":0,"ix":3},"m":1,"ix":2,"nm":"Trim Paths 1","mn":"ADBE Vector Filter - Trim","hd":false}],"ip":10,"op":130,"st":10,"bm":0},{"ddd":0,"ind":10,"ty":4,"nm":"Shape Layer 21","sr":1,"ks":{"o":{"a":0,"k":100,"ix":11},"r":{"a":0,"k":0,"ix":10},"p":{"a":0,"k":[1023.877,677.5,0],"ix":2,"l":2},"a":{"a":0,"k":[223.877,77.5,0],"ix":1,"l":2},"s":{"a":0,"k":[100,100,100],"ix":6,"l":2}},"ao":0,"shapes":[{"ty":"gr","it":[{"ind":0,"ty":"sh","ix":1,"ks":{"a":0,"k":{"i":[[6,-74],[64,2],[-4,140],[60.024,-36.015],[164,2],[3.418,92.284],[0,0],[-7.499,-0.114],[0.25,-20.75],[0,0]],"o":[[-6,74],[-64,-2],[4,-140],[-60,36],[-164,-2],[-3.418,-92.284],[0,0],[32.75,0.5],[-0.096,8.003],[0,0]],"v":[[926,330],[712,440],[608,288],[462,174],[312,332],[100,136],[159.25,49],[263,49.5],[292,67.75],[292,104.25]],"c":false},"ix":2},"nm":"Path 1","mn":"ADBE Vector Shape - Group","hd":false},{"ty":"st","c":{"a":0,"k":[1,1,1,1],"ix":3},"o":{"a":0,"k":100,"ix":4},"w":{"a":0,"k":20,"ix":5},"lc":2,"lj":2,"bm":0,"nm":"Stroke 1","mn":"ADBE Vector Graphic - Stroke","hd":false},{"ty":"tr","p":{"a":0,"k":[0,0],"ix":2},"a":{"a":0,"k":[0,0],"ix":1},"s":{"a":0,"k":[100,100],"ix":3},"r":{"a":0,"k":0,"ix":6},"o":{"a":0,"k":100,"ix":7},"sk":{"a":0,"k":0,"ix":4},"sa":{"a":0,"k":0,"ix":5},"nm":"Transform"}],"nm":"Shape 1","np":3,"cix":2,"bm":0,"ix":1,"mn":"ADBE Vector Group","hd":false},{"ty":"tm","s":{"a":1,"k":[{"i":{"x":[0],"y":[1.004]},"o":{"x":[0.167],"y":[0.167]},"t":10,"s":[0]},{"t":70,"s":[100]}],"ix":1},"e":{"a":1,"k":[{"i":{"x":[0.142],"y":[1.005]},"o":{"x":[0.167],"y":[0.167]},"t":10,"s":[0]},{"t":90,"s":[88.5]}],"ix":2},"o":{"a":0,"k":0,"ix":3},"m":1,"ix":2,"nm":"Trim Paths 1","mn":"ADBE Vector Filter - Trim","hd":false}],"ip":10,"op":130,"st":10,"bm":0},{"ddd":0,"ind":11,"ty":4,"nm":"Shape Layer 20","sr":1,"ks":{"o":{"a":0,"k":100,"ix":11},"r":{"a":0,"k":0,"ix":10},"p":{"a":0,"k":[535.75,550.5,0],"ix":2,"l":2},"a":{"a":0,"k":[-264.25,-49.5,0],"ix":1,"l":2},"s":{"a":0,"k":[100,100,100],"ix":6,"l":2}},"ao":0,"shapes":[{"ty":"gr","it":[{"ind":0,"ty":"sh","ix":1,"ks":{"a":0,"k":{"i":[[2,210],[-34,-58],[46,-30],[10,-54],[-96,-8],[-86,90],[0,0],[0,0],[0,17.5],[0,0],[0,0],[-10.407,-11.223],[0,0]],"o":[[-2,-210],[34,58],[-46,30],[-10,54],[96,8],[86,-90],[0,0],[0,0],[0,-17.5],[0,0],[0,0],[12.75,13.75],[0,0]],"v":[[-894,-246],[-632,-290],[-640,-124],[-760,18],[-688,206],[-480,92],[-303.75,-1],[-247,-35],[-227,-70.25],[-227.5,-95.25],[-227,-65.25],[-211,-39.75],[-152.25,-1.75]],"c":false},"ix":2},"nm":"Path 1","mn":"ADBE Vector Shape - Group","hd":false},{"ty":"st","c":{"a":0,"k":[0.192156862745,0.16862745098,0.274509803922,1],"ix":3},"o":{"a":0,"k":100,"ix":4},"w":{"a":0,"k":20,"ix":5},"lc":2,"lj":2,"bm":0,"nm":"Stroke 1","mn":"ADBE Vector Graphic - Stroke","hd":false},{"ty":"tr","p":{"a":0,"k":[0,0],"ix":2},"a":{"a":0,"k":[0,0],"ix":1},"s":{"a":0,"k":[100,100],"ix":3},"r":{"a":0,"k":0,"ix":6},"o":{"a":0,"k":100,"ix":7},"sk":{"a":0,"k":0,"ix":4},"sa":{"a":0,"k":0,"ix":5},"nm":"Transform"}],"nm":"Shape 1","np":3,"cix":2,"bm":0,"ix":1,"mn":"ADBE Vector Group","hd":false},{"ty":"tm","s":{"a":1,"k":[{"i":{"x":[0],"y":[0.988]},"o":{"x":[0.167],"y":[0.167]},"t":6,"s":[0]},{"t":66,"s":[100]}],"ix":1},"e":{"a":1,"k":[{"i":{"x":[0.154],"y":[0.984]},"o":{"x":[0.167],"y":[0.167]},"t":6,"s":[0]},{"t":86,"s":[84.4]}],"ix":2},"o":{"a":0,"k":0,"ix":3},"m":1,"ix":2,"nm":"Trim Paths 1","mn":"ADBE Vector Filter - Trim","hd":false}],"ip":6,"op":126,"st":6,"bm":0},{"ddd":0,"ind":12,"ty":4,"nm":"Shape Layer 19","sr":1,"ks":{"o":{"a":0,"k":100,"ix":11},"r":{"a":0,"k":0,"ix":10},"p":{"a":0,"k":[573.25,665.25,0],"ix":2,"l":2},"a":{"a":0,"k":[-226.75,65.25,0],"ix":1,"l":2},"s":{"a":0,"k":[100,100,100],"ix":6,"l":2}},"ao":0,"shapes":[{"ty":"gr","it":[{"ind":0,"ty":"sh","ix":1,"ks":{"a":0,"k":{"i":[[-46,-6],[-6,66],[82,4],[10,-94],[-52,0],[28,120],[12,126],[0,0],[0,0]],"o":[[46,6],[6,-66],[-82,-4],[-10,94],[52,0],[-28,-120],[-12,-126],[0,0],[0,0]],"v":[[-552,672],[-362,420],[-506,272],[-658,376],[-486,528],[-316,384],[-450,172],[-321.25,65.25],[-132.25,65.25]],"c":false},"ix":2},"nm":"Path 1","mn":"ADBE Vector Shape - Group","hd":false},{"ty":"st","c":{"a":0,"k":[0.192156862745,0.16862745098,0.274509803922,1],"ix":3},"o":{"a":0,"k":100,"ix":4},"w":{"a":0,"k":20,"ix":5},"lc":2,"lj":2,"bm":0,"nm":"Stroke 1","mn":"ADBE Vector Graphic - Stroke","hd":false},{"ty":"tr","p":{"a":0,"k":[0,0],"ix":2},"a":{"a":0,"k":[0,0],"ix":1},"s":{"a":0,"k":[100,100],"ix":3},"r":{"a":0,"k":0,"ix":6},"o":{"a":0,"k":100,"ix":7},"sk":{"a":0,"k":0,"ix":4},"sa":{"a":0,"k":0,"ix":5},"nm":"Transform"}],"nm":"Shape 1","np":3,"cix":2,"bm":0,"ix":1,"mn":"ADBE Vector Group","hd":false},{"ty":"tm","s":{"a":1,"k":[{"i":{"x":[0],"y":[0.977]},"o":{"x":[0.167],"y":[0.167]},"t":6,"s":[0]},{"t":66,"s":[100]}],"ix":1},"e":{"a":1,"k":[{"i":{"x":[0.155],"y":[0.971]},"o":{"x":[0.167],"y":[0.167]},"t":6,"s":[0]},{"t":86,"s":[90.1]}],"ix":2},"o":{"a":0,"k":0,"ix":3},"m":1,"ix":2,"nm":"Trim Paths 1","mn":"ADBE Vector Filter - Trim","hd":false}],"ip":6,"op":126,"st":6,"bm":0},{"ddd":0,"ind":13,"ty":4,"nm":"Shape Layer 18","sr":1,"ks":{"o":{"a":0,"k":100,"ix":11},"r":{"a":0,"k":0,"ix":10},"p":{"a":0,"k":[798.269,536.375,0],"ix":2,"l":2},"a":{"a":0,"k":[-1.731,-63.625,0],"ix":1,"l":2},"s":{"a":0,"k":[100,100,100],"ix":6,"l":2}},"ao":0,"shapes":[{"ty":"gr","it":[{"ind":0,"ty":"sh","ix":1,"ks":{"a":0,"k":{"i":[[-174,2],[-6,-86],[45.629,2.444],[2,-134],[-92,-2],[0,0],[-12.249,0.144],[1.5,-19.25],[2.75,-9.25]],"o":[[174,-2],[6,86],[-45.629,-2.444],[-2,134],[22.085,0.48],[0,0],[21.25,-0.25],[-2.118,27.186],[-2.75,9.25]],"v":[[-170,-702],[36,-540],[-124,-452],[-288,-314],[-158,-106],[-66.5,-102.75],[42,-102.75],[62.5,-84],[56.25,-24.5]],"c":false},"ix":2},"nm":"Path 1","mn":"ADBE Vector Shape - Group","hd":false},{"ty":"st","c":{"a":0,"k":[0.192156862745,0.16862745098,0.274509803922,1],"ix":3},"o":{"a":0,"k":100,"ix":4},"w":{"a":0,"k":20,"ix":5},"lc":2,"lj":2,"bm":0,"nm":"Stroke 1","mn":"ADBE Vector Graphic - Stroke","hd":false},{"ty":"tr","p":{"a":0,"k":[0,0],"ix":2},"a":{"a":0,"k":[0,0],"ix":1},"s":{"a":0,"k":[100,100],"ix":3},"r":{"a":0,"k":0,"ix":6},"o":{"a":0,"k":100,"ix":7},"sk":{"a":0,"k":0,"ix":4},"sa":{"a":0,"k":0,"ix":5},"nm":"Transform"}],"nm":"Shape 1","np":3,"cix":2,"bm":0,"ix":1,"mn":"ADBE Vector Group","hd":false},{"ty":"tm","s":{"a":1,"k":[{"i":{"x":[0],"y":[0.994]},"o":{"x":[0.167],"y":[0.167]},"t":6,"s":[0]},{"t":66,"s":[100]}],"ix":1},"e":{"a":1,"k":[{"i":{"x":[0.158],"y":[0.992]},"o":{"x":[0.167],"y":[0.167]},"t":6,"s":[0]},{"t":86,"s":[84.7]}],"ix":2},"o":{"a":0,"k":0,"ix":3},"m":1,"ix":2,"nm":"Trim Paths 1","mn":"ADBE Vector Filter - Trim","hd":false}],"ip":6,"op":126,"st":6,"bm":0},{"ddd":0,"ind":14,"ty":4,"nm":"Shape Layer 17","sr":1,"ks":{"o":{"a":0,"k":100,"ix":11},"r":{"a":0,"k":0,"ix":10},"p":{"a":0,"k":[795,541.75,0],"ix":2,"l":2},"a":{"a":0,"k":[-5,-58.25,0],"ix":1,"l":2},"s":{"a":0,"k":[100,100,100],"ix":6,"l":2}},"ao":0,"shapes":[{"ty":"gr","it":[{"ind":0,"ty":"sh","ix":1,"ks":{"a":0,"k":{"i":[[26,-50],[-120,-8],[0,68],[72.477,5.575],[-2,-80],[-76,0],[2,-128],[0,0],[0,0]],"o":[[-26,50],[120,8],[0,-68],[-72.477,-5.575],[3.652,146.078],[76,0],[-2,128],[0,0],[0,0]],"v":[[-920,-114],[-512,-256],[-334,-454],[-434,-564],[-584,-476],[-402,-332],[-174,-194],[-69.5,-58.25],[59.5,-58.25]],"c":false},"ix":2},"nm":"Path 1","mn":"ADBE Vector Shape - Group","hd":false},{"ty":"st","c":{"a":0,"k":[0.192156862745,0.16862745098,0.274509803922,1],"ix":3},"o":{"a":0,"k":100,"ix":4},"w":{"a":0,"k":20,"ix":5},"lc":2,"lj":2,"bm":0,"nm":"Stroke 1","mn":"ADBE Vector Graphic - Stroke","hd":false},{"ty":"tr","p":{"a":0,"k":[0,0],"ix":2},"a":{"a":0,"k":[0,0],"ix":1},"s":{"a":0,"k":[100,100],"ix":3},"r":{"a":0,"k":0,"ix":6},"o":{"a":0,"k":100,"ix":7},"sk":{"a":0,"k":0,"ix":4},"sa":{"a":0,"k":0,"ix":5},"nm":"Transform"}],"nm":"Shape 1","np":3,"cix":2,"bm":0,"ix":1,"mn":"ADBE Vector Group","hd":false},{"ty":"tm","s":{"a":1,"k":[{"i":{"x":[0],"y":[1.003]},"o":{"x":[0.167],"y":[0.167]},"t":6,"s":[0]},{"t":66,"s":[100]}],"ix":1},"e":{"a":1,"k":[{"i":{"x":[0.154],"y":[1.003]},"o":{"x":[0.167],"y":[0.167]},"t":6,"s":[0]},{"t":86,"s":[93.7]}],"ix":2},"o":{"a":0,"k":0,"ix":3},"m":1,"ix":2,"nm":"Trim Paths 1","mn":"ADBE Vector Filter - Trim","hd":false}],"ip":6,"op":126,"st":6,"bm":0},{"ddd":0,"ind":15,"ty":4,"nm":"Shape Layer 16","sr":1,"ks":{"o":{"a":0,"k":100,"ix":11},"r":{"a":0,"k":0,"ix":10},"p":{"a":0,"k":[799.875,584.75,0],"ix":2,"l":2},"a":{"a":0,"k":[-0.125,-15.25,0],"ix":1,"l":2},"s":{"a":0,"k":[100,100,100],"ix":6,"l":2}},"ao":0,"shapes":[{"ty":"gr","it":[{"ind":0,"ty":"sh","ix":1,"ks":{"a":0,"k":{"i":[[74,4],[6,192],[-190,-2],[-2,-108],[80.016,-1.212],[-2,214],[0,0],[0,0],[0,0],[0,0]],"o":[[-74,-4],[-6,-192],[77.996,0.821],[2,108],[-80.016,1.212],[2,-214],[0,0],[0,0],[0,0],[0,0]],"v":[[52,688],[-154,516],[68,180],[234,294],[38,428],[-206,180],[-96,-15.25],[95.75,-15.25],[-0.25,-15.25],[-0.25,24.25]],"c":false},"ix":2},"nm":"Path 1","mn":"ADBE Vector Shape - Group","hd":false},{"ty":"st","c":{"a":0,"k":[0.192156862745,0.16862745098,0.274509803922,1],"ix":3},"o":{"a":0,"k":100,"ix":4},"w":{"a":0,"k":20,"ix":5},"lc":2,"lj":2,"bm":0,"nm":"Stroke 1","mn":"ADBE Vector Graphic - Stroke","hd":false},{"ty":"tr","p":{"a":0,"k":[0,0],"ix":2},"a":{"a":0,"k":[0,0],"ix":1},"s":{"a":0,"k":[100,100],"ix":3},"r":{"a":0,"k":0,"ix":6},"o":{"a":0,"k":100,"ix":7},"sk":{"a":0,"k":0,"ix":4},"sa":{"a":0,"k":0,"ix":5},"nm":"Transform"}],"nm":"Shape 1","np":3,"cix":2,"bm":0,"ix":1,"mn":"ADBE Vector Group","hd":false},{"ty":"tm","s":{"a":1,"k":[{"i":{"x":[0],"y":[0.987]},"o":{"x":[0.167],"y":[0.167]},"t":6,"s":[0]},{"t":66,"s":[100]}],"ix":1},"e":{"a":1,"k":[{"i":{"x":[0.154],"y":[0.983]},"o":{"x":[0.167],"y":[0.167]},"t":6,"s":[0]},{"t":86,"s":[85.5]}],"ix":2},"o":{"a":0,"k":0,"ix":3},"m":1,"ix":2,"nm":"Trim Paths 1","mn":"ADBE Vector Filter - Trim","hd":false}],"ip":6,"op":126,"st":6,"bm":0},{"ddd":0,"ind":16,"ty":4,"nm":"Shape Layer 15","sr":1,"ks":{"o":{"a":0,"k":100,"ix":11},"r":{"a":0,"k":0,"ix":10},"p":{"a":0,"k":[802.875,665.67,0],"ix":2,"l":2},"a":{"a":0,"k":[2.875,65.67,0],"ix":1,"l":2},"s":{"a":0,"k":[100,100,100],"ix":6,"l":2}},"ao":0,"shapes":[{"ty":"gr","it":[{"ind":0,"ty":"sh","ix":1,"ks":{"a":0,"k":{"i":[[-155.945,-10.829],[-22,88],[80,0],[-6,-156],[-112,4],[-10,214],[0,0],[-8.246,-0.358],[0,-19],[15,-0.25],[8.996,-0.261],[-0.273,-17.998],[-14.75,0],[0,0]],"o":[[432,30],[18.592,-74.366],[-80,0],[6,156],[112,-4],[10,-214],[0,0],[17.25,0.75],[0,19],[-10.002,0.167],[-17.25,0.5],[0.25,16.5],[10.25,0],[0,0]],"v":[[-854,432],[-380,126],[-554,-72],[-728,136],[-512,424],[-298,226],[-66.5,28.75],[50,28.75],[64.75,48.5],[49.75,66.25],[-48.5,66.25],[-65.5,86.25],[-48.5,102.75],[69.5,102.75]],"c":false},"ix":2},"nm":"Path 1","mn":"ADBE Vector Shape - Group","hd":false},{"ty":"st","c":{"a":0,"k":[0.192156862745,0.16862745098,0.274509803922,1],"ix":3},"o":{"a":0,"k":100,"ix":4},"w":{"a":0,"k":20,"ix":5},"lc":2,"lj":2,"bm":0,"nm":"Stroke 1","mn":"ADBE Vector Graphic - Stroke","hd":false},{"ty":"tr","p":{"a":0,"k":[0,0],"ix":2},"a":{"a":0,"k":[0,0],"ix":1},"s":{"a":0,"k":[100,100],"ix":3},"r":{"a":0,"k":0,"ix":6},"o":{"a":0,"k":100,"ix":7},"sk":{"a":0,"k":0,"ix":4},"sa":{"a":0,"k":0,"ix":5},"nm":"Transform"}],"nm":"Shape 1","np":3,"cix":2,"bm":0,"ix":1,"mn":"ADBE Vector Group","hd":false},{"ty":"tm","s":{"a":1,"k":[{"i":{"x":[0],"y":[1.006]},"o":{"x":[0.167],"y":[0.167]},"t":6,"s":[0]},{"t":66,"s":[100]}],"ix":1},"e":{"a":1,"k":[{"i":{"x":[0.151],"y":[1.009]},"o":{"x":[0.167],"y":[0.167]},"t":6,"s":[0]},{"t":86,"s":[83.6]}],"ix":2},"o":{"a":0,"k":0,"ix":3},"m":1,"ix":2,"nm":"Trim Paths 1","mn":"ADBE Vector Filter - Trim","hd":false}],"ip":6,"op":126,"st":6,"bm":0},{"ddd":0,"ind":17,"ty":4,"nm":"Shape Layer 14","sr":1,"ks":{"o":{"a":0,"k":100,"ix":11},"r":{"a":0,"k":0,"ix":10},"p":{"a":0,"k":[1026.375,528.806,0],"ix":2,"l":2},"a":{"a":0,"k":[226.375,-71.194,0],"ix":1,"l":2},"s":{"a":0,"k":[100,100,100],"ix":6,"l":2}},"ao":0,"shapes":[{"ty":"gr","it":[{"ind":0,"ty":"sh","ix":1,"ks":{"a":0,"k":{"i":[[-220,38],[8,-84],[114,2],[8,66],[-42,8],[-2,-76],[0,0],[0.174,-7.498],[-9,-0.5],[-6.254,0.11],[0.25,14],[0,0]],"o":[[220,-38],[-4.86,51.033],[-114,-2],[-8,-66],[42,-8],[2,76],[0,0],[-0.25,10.75],[6.49,0.361],[14.25,-0.25],[-0.116,-6.499],[0,0]],"v":[[296,-690],[506,-448],[224,-148],[-84,-264],[10,-414],[164,-302],[164,-103],[163.5,-45.25],[177.5,-35.75],[276.75,-35.75],[291.75,-49],[291.75,-102.75]],"c":false},"ix":2},"nm":"Path 1","mn":"ADBE Vector Shape - Group","hd":false},{"ty":"st","c":{"a":0,"k":[0.192156862745,0.16862745098,0.274509803922,1],"ix":3},"o":{"a":0,"k":100,"ix":4},"w":{"a":0,"k":20,"ix":5},"lc":2,"lj":2,"bm":0,"nm":"Stroke 1","mn":"ADBE Vector Graphic - Stroke","hd":false},{"ty":"tr","p":{"a":0,"k":[0,0],"ix":2},"a":{"a":0,"k":[0,0],"ix":1},"s":{"a":0,"k":[100,100],"ix":3},"r":{"a":0,"k":0,"ix":6},"o":{"a":0,"k":100,"ix":7},"sk":{"a":0,"k":0,"ix":4},"sa":{"a":0,"k":0,"ix":5},"nm":"Transform"}],"nm":"Shape 2","np":3,"cix":2,"bm":0,"ix":1,"mn":"ADBE Vector Group","hd":false},{"ty":"gr","it":[{"ty":"st","c":{"a":0,"k":[0.192156862745,0.16862745098,0.274509803922,1],"ix":3},"o":{"a":0,"k":100,"ix":4},"w":{"a":0,"k":20,"ix":5},"lc":1,"lj":1,"ml":4,"bm":0,"nm":"Stroke 1","mn":"ADBE Vector Graphic - Stroke","hd":false},{"ty":"tr","p":{"a":0,"k":[0,0],"ix":2},"a":{"a":0,"k":[0,0],"ix":1},"s":{"a":0,"k":[100,100],"ix":3},"r":{"a":0,"k":0,"ix":6},"o":{"a":0,"k":100,"ix":7},"sk":{"a":0,"k":0,"ix":4},"sa":{"a":0,"k":0,"ix":5},"nm":"Transform"}],"nm":"Shape 1","np":2,"cix":2,"bm":0,"ix":2,"mn":"ADBE Vector Group","hd":false},{"ty":"tm","s":{"a":1,"k":[{"i":{"x":[0],"y":[1]},"o":{"x":[0.167],"y":[0.167]},"t":6,"s":[0]},{"t":66,"s":[100]}],"ix":1},"e":{"a":1,"k":[{"i":{"x":[0.155],"y":[1]},"o":{"x":[0.167],"y":[0.167]},"t":6,"s":[0]},{"t":86,"s":[87.3]}],"ix":2},"o":{"a":0,"k":0,"ix":3},"m":1,"ix":3,"nm":"Trim Paths 1","mn":"ADBE Vector Filter - Trim","hd":false}],"ip":6,"op":126,"st":6,"bm":0},{"ddd":0,"ind":18,"ty":4,"nm":"Shape Layer 13","sr":1,"ks":{"o":{"a":0,"k":100,"ix":11},"r":{"a":0,"k":0,"ix":10},"p":{"a":0,"k":[1026.875,523,0],"ix":2,"l":2},"a":{"a":0,"k":[226.875,-77,0],"ix":1,"l":2},"s":{"a":0,"k":[100,100,100],"ix":6,"l":2}},"ao":0,"shapes":[{"ty":"gr","it":[{"ind":0,"ty":"sh","ix":1,"ks":{"a":0,"k":{"i":[[90,34],[10,-96],[-102,4],[2,-140],[100,4],[-2,116],[96,0],[8,-84],[-88,-4],[0,0],[0,0]],"o":[[-90,-34],[-10,96],[102,-4],[-2,140],[-100,-4],[2,-116],[-96,0],[-8,84],[88,4],[0,0],[0,0]],"v":[[1036,-418],[404,-504],[622,-354],[776,-144],[582,40],[450,-178],[228,-354],[-26,-244],[102,-82],[168.25,-77],[285.5,-77]],"c":false},"ix":2},"nm":"Path 1","mn":"ADBE Vector Shape - Group","hd":false},{"ty":"st","c":{"a":0,"k":[0.192156862745,0.16862745098,0.274509803922,1],"ix":3},"o":{"a":0,"k":100,"ix":4},"w":{"a":0,"k":20,"ix":5},"lc":2,"lj":2,"bm":0,"nm":"Stroke 1","mn":"ADBE Vector Graphic - Stroke","hd":false},{"ty":"tr","p":{"a":0,"k":[0,0],"ix":2},"a":{"a":0,"k":[0,0],"ix":1},"s":{"a":0,"k":[100,100],"ix":3},"r":{"a":0,"k":0,"ix":6},"o":{"a":0,"k":100,"ix":7},"sk":{"a":0,"k":0,"ix":4},"sa":{"a":0,"k":0,"ix":5},"nm":"Transform"}],"nm":"Shape 1","np":3,"cix":2,"bm":0,"ix":1,"mn":"ADBE Vector Group","hd":false},{"ty":"tm","s":{"a":1,"k":[{"i":{"x":[0],"y":[1.004]},"o":{"x":[0.167],"y":[0.167]},"t":6,"s":[0]},{"t":66,"s":[100]}],"ix":1},"e":{"a":1,"k":[{"i":{"x":[0.15],"y":[1.004]},"o":{"x":[0.167],"y":[0.167]},"t":6,"s":[0]},{"t":86,"s":[96]}],"ix":2},"o":{"a":0,"k":0,"ix":3},"m":1,"ix":2,"nm":"Trim Paths 1","mn":"ADBE Vector Filter - Trim","hd":false}],"ip":6,"op":126,"st":6,"bm":0},{"ddd":0,"ind":19,"ty":4,"nm":"Shape Layer 12","sr":1,"ks":{"o":{"a":0,"k":100,"ix":11},"r":{"a":0,"k":0,"ix":10},"p":{"a":0,"k":[1027.875,605,0],"ix":2,"l":2},"a":{"a":0,"k":[227.875,5,0],"ix":1,"l":2},"s":{"a":0,"k":[100,100,100],"ix":6,"l":2}},"ao":0,"shapes":[{"ty":"gr","it":[{"ind":0,"ty":"sh","ix":1,"ks":{"a":0,"k":{"i":[[-24,132],[106,0],[4.23,-114.202],[154,0],[4,150],[0,0],[0,0],[0,0],[0,0]],"o":[[24,-132],[-106,0],[-4.229,114.202],[-154,0],[-4,-150],[0,0],[0,0],[0,0],[0,0]],"v":[[900,326],[668,86],[498,274],[230,440],[18,144],[133.25,4.75],[322.5,4.75],[227,4.75],[227,42.5]],"c":false},"ix":2},"nm":"Path 1","mn":"ADBE Vector Shape - Group","hd":false},{"ty":"st","c":{"a":0,"k":[0.192156862745,0.16862745098,0.274509803922,1],"ix":3},"o":{"a":0,"k":100,"ix":4},"w":{"a":0,"k":20,"ix":5},"lc":2,"lj":2,"bm":0,"nm":"Stroke 1","mn":"ADBE Vector Graphic - Stroke","hd":false},{"ty":"tr","p":{"a":0,"k":[0,0],"ix":2},"a":{"a":0,"k":[0,0],"ix":1},"s":{"a":0,"k":[100,100],"ix":3},"r":{"a":0,"k":0,"ix":6},"o":{"a":0,"k":100,"ix":7},"sk":{"a":0,"k":0,"ix":4},"sa":{"a":0,"k":0,"ix":5},"nm":"Transform"}],"nm":"Shape 1","np":3,"cix":2,"bm":0,"ix":1,"mn":"ADBE Vector Group","hd":false},{"ty":"tm","s":{"a":1,"k":[{"i":{"x":[0],"y":[0.994]},"o":{"x":[0.167],"y":[0.167]},"t":6,"s":[0]},{"t":66,"s":[100]}],"ix":1},"e":{"a":1,"k":[{"i":{"x":[0.155],"y":[0.992]},"o":{"x":[0.167],"y":[0.167]},"t":6,"s":[0]},{"t":86,"s":[83.5]}],"ix":2},"o":{"a":0,"k":0,"ix":3},"m":1,"ix":2,"nm":"Trim Paths 1","mn":"ADBE Vector Filter - Trim","hd":false}],"ip":6,"op":126,"st":6,"bm":0},{"ddd":0,"ind":20,"ty":4,"nm":"Shape Layer 11","sr":1,"ks":{"o":{"a":0,"k":100,"ix":11},"r":{"a":0,"k":0,"ix":10},"p":{"a":0,"k":[1023.877,677.5,0],"ix":2,"l":2},"a":{"a":0,"k":[223.877,77.5,0],"ix":1,"l":2},"s":{"a":0,"k":[100,100,100],"ix":6,"l":2}},"ao":0,"shapes":[{"ty":"gr","it":[{"ind":0,"ty":"sh","ix":1,"ks":{"a":0,"k":{"i":[[6,-74],[64,2],[-4,140],[60.024,-36.015],[164,2],[3.418,92.284],[0,0],[-7.499,-0.114],[0.25,-20.75],[0,0]],"o":[[-6,74],[-64,-2],[4,-140],[-60,36],[-164,-2],[-3.418,-92.284],[0,0],[32.75,0.5],[-0.096,8.003],[0,0]],"v":[[926,330],[712,440],[608,288],[462,174],[312,332],[100,136],[159.25,49],[263,49.5],[292,67.75],[292,104.25]],"c":false},"ix":2},"nm":"Path 1","mn":"ADBE Vector Shape - Group","hd":false},{"ty":"st","c":{"a":0,"k":[0.192156862745,0.16862745098,0.274509803922,1],"ix":3},"o":{"a":0,"k":100,"ix":4},"w":{"a":0,"k":20,"ix":5},"lc":2,"lj":2,"bm":0,"nm":"Stroke 1","mn":"ADBE Vector Graphic - Stroke","hd":false},{"ty":"tr","p":{"a":0,"k":[0,0],"ix":2},"a":{"a":0,"k":[0,0],"ix":1},"s":{"a":0,"k":[100,100],"ix":3},"r":{"a":0,"k":0,"ix":6},"o":{"a":0,"k":100,"ix":7},"sk":{"a":0,"k":0,"ix":4},"sa":{"a":0,"k":0,"ix":5},"nm":"Transform"}],"nm":"Shape 1","np":3,"cix":2,"bm":0,"ix":1,"mn":"ADBE Vector Group","hd":false},{"ty":"tm","s":{"a":1,"k":[{"i":{"x":[0],"y":[1.004]},"o":{"x":[0.167],"y":[0.167]},"t":6,"s":[0]},{"t":66,"s":[100]}],"ix":1},"e":{"a":1,"k":[{"i":{"x":[0.142],"y":[1.005]},"o":{"x":[0.167],"y":[0.167]},"t":6,"s":[0]},{"t":86,"s":[88.5]}],"ix":2},"o":{"a":0,"k":0,"ix":3},"m":1,"ix":2,"nm":"Trim Paths 1","mn":"ADBE Vector Filter - Trim","hd":false}],"ip":6,"op":126,"st":6,"bm":0},{"ddd":0,"ind":21,"ty":4,"nm":"Shape Layer 10","sr":1,"ks":{"o":{"a":0,"k":100,"ix":11},"r":{"a":0,"k":0,"ix":10},"p":{"a":0,"k":[1023.877,677.5,0],"ix":2,"l":2},"a":{"a":0,"k":[223.877,77.5,0],"ix":1,"l":2},"s":{"a":0,"k":[100,100,100],"ix":6,"l":2}},"ao":0,"shapes":[{"ty":"gr","it":[{"ind":0,"ty":"sh","ix":1,"ks":{"a":0,"k":{"i":[[6,-74],[64,2],[-4,140],[60.024,-36.015],[164,2],[3.418,92.284],[0,0],[-7.499,-0.114],[0.25,-20.75],[0,0]],"o":[[-6,74],[-64,-2],[4,-140],[-60,36],[-164,-2],[-3.418,-92.284],[0,0],[32.75,0.5],[-0.096,8.003],[0,0]],"v":[[926,330],[712,440],[608,288],[462,174],[312,332],[100,136],[159.25,49],[263,49.5],[292,67.75],[292,104.25]],"c":false},"ix":2},"nm":"Path 1","mn":"ADBE Vector Shape - Group","hd":false},{"ty":"st","c":{"a":0,"k":[0.525490196078,0.270588235294,1,1],"ix":3},"o":{"a":0,"k":100,"ix":4},"w":{"a":0,"k":20,"ix":5},"lc":2,"lj":2,"bm":0,"nm":"Stroke 1","mn":"ADBE Vector Graphic - Stroke","hd":false},{"ty":"tr","p":{"a":0,"k":[0,0],"ix":2},"a":{"a":0,"k":[0,0],"ix":1},"s":{"a":0,"k":[100,100],"ix":3},"r":{"a":0,"k":0,"ix":6},"o":{"a":0,"k":100,"ix":7},"sk":{"a":0,"k":0,"ix":4},"sa":{"a":0,"k":0,"ix":5},"nm":"Transform"}],"nm":"Shape 1","np":3,"cix":2,"bm":0,"ix":1,"mn":"ADBE Vector Group","hd":false},{"ty":"tm","s":{"a":1,"k":[{"i":{"x":[0],"y":[1.004]},"o":{"x":[0.167],"y":[0.167]},"t":0,"s":[0]},{"t":60,"s":[100]}],"ix":1},"e":{"a":1,"k":[{"i":{"x":[0.142],"y":[1.005]},"o":{"x":[0.167],"y":[0.167]},"t":0,"s":[0]},{"t":80,"s":[88.5]}],"ix":2},"o":{"a":0,"k":0,"ix":3},"m":1,"ix":2,"nm":"Trim Paths 1","mn":"ADBE Vector Filter - Trim","hd":false}],"ip":0,"op":120,"st":0,"bm":0},{"ddd":0,"ind":22,"ty":4,"nm":"Shape Layer 9","sr":1,"ks":{"o":{"a":0,"k":100,"ix":11},"r":{"a":0,"k":0,"ix":10},"p":{"a":0,"k":[1027.875,605,0],"ix":2,"l":2},"a":{"a":0,"k":[227.875,5,0],"ix":1,"l":2},"s":{"a":0,"k":[100,100,100],"ix":6,"l":2}},"ao":0,"shapes":[{"ty":"gr","it":[{"ind":0,"ty":"sh","ix":1,"ks":{"a":0,"k":{"i":[[-24,132],[106,0],[4.23,-114.202],[154,0],[4,150],[0,0],[0,0],[0,0],[0,0]],"o":[[24,-132],[-106,0],[-4.229,114.202],[-154,0],[-4,-150],[0,0],[0,0],[0,0],[0,0]],"v":[[900,326],[668,86],[498,274],[230,440],[18,144],[133.25,4.75],[322.5,4.75],[227,4.75],[227,42.5]],"c":false},"ix":2},"nm":"Path 1","mn":"ADBE Vector Shape - Group","hd":false},{"ty":"st","c":{"a":0,"k":[0.525490196078,0.270588235294,1,1],"ix":3},"o":{"a":0,"k":100,"ix":4},"w":{"a":0,"k":20,"ix":5},"lc":2,"lj":2,"bm":0,"nm":"Stroke 1","mn":"ADBE Vector Graphic - Stroke","hd":false},{"ty":"tr","p":{"a":0,"k":[0,0],"ix":2},"a":{"a":0,"k":[0,0],"ix":1},"s":{"a":0,"k":[100,100],"ix":3},"r":{"a":0,"k":0,"ix":6},"o":{"a":0,"k":100,"ix":7},"sk":{"a":0,"k":0,"ix":4},"sa":{"a":0,"k":0,"ix":5},"nm":"Transform"}],"nm":"Shape 1","np":3,"cix":2,"bm":0,"ix":1,"mn":"ADBE Vector Group","hd":false},{"ty":"tm","s":{"a":1,"k":[{"i":{"x":[0],"y":[0.994]},"o":{"x":[0.167],"y":[0.167]},"t":0,"s":[0]},{"t":60,"s":[100]}],"ix":1},"e":{"a":1,"k":[{"i":{"x":[0.155],"y":[0.992]},"o":{"x":[0.167],"y":[0.167]},"t":0,"s":[0]},{"t":80,"s":[83.5]}],"ix":2},"o":{"a":0,"k":0,"ix":3},"m":1,"ix":2,"nm":"Trim Paths 1","mn":"ADBE Vector Filter - Trim","hd":false}],"ip":0,"op":120,"st":0,"bm":0},{"ddd":0,"ind":23,"ty":4,"nm":"Shape Layer 8","sr":1,"ks":{"o":{"a":0,"k":100,"ix":11},"r":{"a":0,"k":0,"ix":10},"p":{"a":0,"k":[1026.875,523,0],"ix":2,"l":2},"a":{"a":0,"k":[226.875,-77,0],"ix":1,"l":2},"s":{"a":0,"k":[100,100,100],"ix":6,"l":2}},"ao":0,"shapes":[{"ty":"gr","it":[{"ind":0,"ty":"sh","ix":1,"ks":{"a":0,"k":{"i":[[90,34],[10,-96],[-102,4],[2,-140],[100,4],[-2,116],[96,0],[8,-84],[-88,-4],[0,0],[0,0]],"o":[[-90,-34],[-10,96],[102,-4],[-2,140],[-100,-4],[2,-116],[-96,0],[-8,84],[88,4],[0,0],[0,0]],"v":[[1036,-418],[404,-504],[622,-354],[776,-144],[582,40],[450,-178],[228,-354],[-26,-244],[102,-82],[168.25,-77],[285.5,-77]],"c":false},"ix":2},"nm":"Path 1","mn":"ADBE Vector Shape - Group","hd":false},{"ty":"st","c":{"a":0,"k":[0.525490196078,0.270588235294,1,1],"ix":3},"o":{"a":0,"k":100,"ix":4},"w":{"a":0,"k":20,"ix":5},"lc":2,"lj":2,"bm":0,"nm":"Stroke 1","mn":"ADBE Vector Graphic - Stroke","hd":false},{"ty":"tr","p":{"a":0,"k":[0,0],"ix":2},"a":{"a":0,"k":[0,0],"ix":1},"s":{"a":0,"k":[100,100],"ix":3},"r":{"a":0,"k":0,"ix":6},"o":{"a":0,"k":100,"ix":7},"sk":{"a":0,"k":0,"ix":4},"sa":{"a":0,"k":0,"ix":5},"nm":"Transform"}],"nm":"Shape 1","np":3,"cix":2,"bm":0,"ix":1,"mn":"ADBE Vector Group","hd":false},{"ty":"tm","s":{"a":1,"k":[{"i":{"x":[0],"y":[1.004]},"o":{"x":[0.167],"y":[0.167]},"t":0,"s":[0]},{"t":60,"s":[100]}],"ix":1},"e":{"a":1,"k":[{"i":{"x":[0.15],"y":[1.004]},"o":{"x":[0.167],"y":[0.167]},"t":0,"s":[0]},{"t":80,"s":[96]}],"ix":2},"o":{"a":0,"k":0,"ix":3},"m":1,"ix":2,"nm":"Trim Paths 1","mn":"ADBE Vector Filter - Trim","hd":false}],"ip":0,"op":120,"st":0,"bm":0},{"ddd":0,"ind":24,"ty":4,"nm":"Shape Layer 7","sr":1,"ks":{"o":{"a":0,"k":100,"ix":11},"r":{"a":0,"k":0,"ix":10},"p":{"a":0,"k":[1026.375,528.806,0],"ix":2,"l":2},"a":{"a":0,"k":[226.375,-71.194,0],"ix":1,"l":2},"s":{"a":0,"k":[100,100,100],"ix":6,"l":2}},"ao":0,"shapes":[{"ty":"gr","it":[{"ind":0,"ty":"sh","ix":1,"ks":{"a":0,"k":{"i":[[-220,38],[8,-84],[114,2],[8,66],[-42,8],[-2,-76],[0,0],[0.174,-7.498],[-9,-0.5],[-6.254,0.11],[0.25,14],[0,0]],"o":[[220,-38],[-4.86,51.033],[-114,-2],[-8,-66],[42,-8],[2,76],[0,0],[-0.25,10.75],[6.49,0.361],[14.25,-0.25],[-0.116,-6.499],[0,0]],"v":[[296,-690],[506,-448],[224,-148],[-84,-264],[10,-414],[164,-302],[164,-103],[163.5,-45.25],[177.5,-35.75],[276.75,-35.75],[291.75,-49],[291.75,-102.75]],"c":false},"ix":2},"nm":"Path 1","mn":"ADBE Vector Shape - Group","hd":false},{"ty":"st","c":{"a":0,"k":[0.525490196078,0.270588235294,1,1],"ix":3},"o":{"a":0,"k":100,"ix":4},"w":{"a":0,"k":20,"ix":5},"lc":2,"lj":2,"bm":0,"nm":"Stroke 1","mn":"ADBE Vector Graphic - Stroke","hd":false},{"ty":"tr","p":{"a":0,"k":[0,0],"ix":2},"a":{"a":0,"k":[0,0],"ix":1},"s":{"a":0,"k":[100,100],"ix":3},"r":{"a":0,"k":0,"ix":6},"o":{"a":0,"k":100,"ix":7},"sk":{"a":0,"k":0,"ix":4},"sa":{"a":0,"k":0,"ix":5},"nm":"Transform"}],"nm":"Shape 2","np":3,"cix":2,"bm":0,"ix":1,"mn":"ADBE Vector Group","hd":false},{"ty":"gr","it":[{"ty":"st","c":{"a":0,"k":[0.525490196078,0.270588235294,1,1],"ix":3},"o":{"a":0,"k":100,"ix":4},"w":{"a":0,"k":20,"ix":5},"lc":1,"lj":1,"ml":4,"bm":0,"nm":"Stroke 1","mn":"ADBE Vector Graphic - Stroke","hd":false},{"ty":"tr","p":{"a":0,"k":[0,0],"ix":2},"a":{"a":0,"k":[0,0],"ix":1},"s":{"a":0,"k":[100,100],"ix":3},"r":{"a":0,"k":0,"ix":6},"o":{"a":0,"k":100,"ix":7},"sk":{"a":0,"k":0,"ix":4},"sa":{"a":0,"k":0,"ix":5},"nm":"Transform"}],"nm":"Shape 1","np":2,"cix":2,"bm":0,"ix":2,"mn":"ADBE Vector Group","hd":false},{"ty":"tm","s":{"a":1,"k":[{"i":{"x":[0],"y":[1]},"o":{"x":[0.167],"y":[0.167]},"t":0,"s":[0]},{"t":60,"s":[100]}],"ix":1},"e":{"a":1,"k":[{"i":{"x":[0.155],"y":[1]},"o":{"x":[0.167],"y":[0.167]},"t":0,"s":[0]},{"t":80,"s":[87.3]}],"ix":2},"o":{"a":0,"k":0,"ix":3},"m":1,"ix":3,"nm":"Trim Paths 1","mn":"ADBE Vector Filter - Trim","hd":false}],"ip":0,"op":120,"st":0,"bm":0},{"ddd":0,"ind":25,"ty":4,"nm":"Shape Layer 6","sr":1,"ks":{"o":{"a":0,"k":100,"ix":11},"r":{"a":0,"k":0,"ix":10},"p":{"a":0,"k":[802.875,665.67,0],"ix":2,"l":2},"a":{"a":0,"k":[2.875,65.67,0],"ix":1,"l":2},"s":{"a":0,"k":[100,100,100],"ix":6,"l":2}},"ao":0,"shapes":[{"ty":"gr","it":[{"ind":0,"ty":"sh","ix":1,"ks":{"a":0,"k":{"i":[[-155.945,-10.829],[-22,88],[80,0],[-6,-156],[-112,4],[-10,214],[0,0],[-8.246,-0.358],[0,-19],[15,-0.25],[8.996,-0.261],[-0.273,-17.998],[-14.75,0],[0,0]],"o":[[432,30],[18.592,-74.366],[-80,0],[6,156],[112,-4],[10,-214],[0,0],[17.25,0.75],[0,19],[-10.002,0.167],[-17.25,0.5],[0.25,16.5],[10.25,0],[0,0]],"v":[[-854,432],[-380,126],[-554,-72],[-728,136],[-512,424],[-298,226],[-66.5,28.75],[50,28.75],[64.75,48.5],[49.75,66.25],[-48.5,66.25],[-65.5,86.25],[-48.5,102.75],[69.5,102.75]],"c":false},"ix":2},"nm":"Path 1","mn":"ADBE Vector Shape - Group","hd":false},{"ty":"st","c":{"a":0,"k":[0.525490196078,0.270588235294,1,1],"ix":3},"o":{"a":0,"k":100,"ix":4},"w":{"a":0,"k":20,"ix":5},"lc":2,"lj":2,"bm":0,"nm":"Stroke 1","mn":"ADBE Vector Graphic - Stroke","hd":false},{"ty":"tr","p":{"a":0,"k":[0,0],"ix":2},"a":{"a":0,"k":[0,0],"ix":1},"s":{"a":0,"k":[100,100],"ix":3},"r":{"a":0,"k":0,"ix":6},"o":{"a":0,"k":100,"ix":7},"sk":{"a":0,"k":0,"ix":4},"sa":{"a":0,"k":0,"ix":5},"nm":"Transform"}],"nm":"Shape 1","np":3,"cix":2,"bm":0,"ix":1,"mn":"ADBE Vector Group","hd":false},{"ty":"tm","s":{"a":1,"k":[{"i":{"x":[0],"y":[1.006]},"o":{"x":[0.167],"y":[0.167]},"t":0,"s":[0]},{"t":60,"s":[100]}],"ix":1},"e":{"a":1,"k":[{"i":{"x":[0.151],"y":[1.009]},"o":{"x":[0.167],"y":[0.167]},"t":0,"s":[0]},{"t":80,"s":[83.6]}],"ix":2},"o":{"a":0,"k":0,"ix":3},"m":1,"ix":2,"nm":"Trim Paths 1","mn":"ADBE Vector Filter - Trim","hd":false}],"ip":0,"op":120,"st":0,"bm":0},{"ddd":0,"ind":26,"ty":4,"nm":"Shape Layer 5","sr":1,"ks":{"o":{"a":0,"k":100,"ix":11},"r":{"a":0,"k":0,"ix":10},"p":{"a":0,"k":[799.875,584.75,0],"ix":2,"l":2},"a":{"a":0,"k":[-0.125,-15.25,0],"ix":1,"l":2},"s":{"a":0,"k":[100,100,100],"ix":6,"l":2}},"ao":0,"shapes":[{"ty":"gr","it":[{"ind":0,"ty":"sh","ix":1,"ks":{"a":0,"k":{"i":[[74,4],[6,192],[-190,-2],[-2,-108],[80.016,-1.212],[-2,214],[0,0],[0,0],[0,0],[0,0]],"o":[[-74,-4],[-6,-192],[77.996,0.821],[2,108],[-80.016,1.212],[2,-214],[0,0],[0,0],[0,0],[0,0]],"v":[[52,688],[-154,516],[68,180],[234,294],[38,428],[-206,180],[-96,-15.25],[95.75,-15.25],[-0.25,-15.25],[-0.25,24.25]],"c":false},"ix":2},"nm":"Path 1","mn":"ADBE Vector Shape - Group","hd":false},{"ty":"st","c":{"a":0,"k":[0.525490196078,0.270588235294,1,1],"ix":3},"o":{"a":0,"k":100,"ix":4},"w":{"a":0,"k":20,"ix":5},"lc":2,"lj":2,"bm":0,"nm":"Stroke 1","mn":"ADBE Vector Graphic - Stroke","hd":false},{"ty":"tr","p":{"a":0,"k":[0,0],"ix":2},"a":{"a":0,"k":[0,0],"ix":1},"s":{"a":0,"k":[100,100],"ix":3},"r":{"a":0,"k":0,"ix":6},"o":{"a":0,"k":100,"ix":7},"sk":{"a":0,"k":0,"ix":4},"sa":{"a":0,"k":0,"ix":5},"nm":"Transform"}],"nm":"Shape 1","np":3,"cix":2,"bm":0,"ix":1,"mn":"ADBE Vector Group","hd":false},{"ty":"tm","s":{"a":1,"k":[{"i":{"x":[0],"y":[0.987]},"o":{"x":[0.167],"y":[0.167]},"t":0,"s":[0]},{"t":60,"s":[100]}],"ix":1},"e":{"a":1,"k":[{"i":{"x":[0.154],"y":[0.983]},"o":{"x":[0.167],"y":[0.167]},"t":0,"s":[0]},{"t":80,"s":[85.5]}],"ix":2},"o":{"a":0,"k":0,"ix":3},"m":1,"ix":2,"nm":"Trim Paths 1","mn":"ADBE Vector Filter - Trim","hd":false}],"ip":0,"op":120,"st":0,"bm":0},{"ddd":0,"ind":27,"ty":4,"nm":"Shape Layer 4","sr":1,"ks":{"o":{"a":0,"k":100,"ix":11},"r":{"a":0,"k":0,"ix":10},"p":{"a":0,"k":[795,541.75,0],"ix":2,"l":2},"a":{"a":0,"k":[-5,-58.25,0],"ix":1,"l":2},"s":{"a":0,"k":[100,100,100],"ix":6,"l":2}},"ao":0,"shapes":[{"ty":"gr","it":[{"ind":0,"ty":"sh","ix":1,"ks":{"a":0,"k":{"i":[[26,-50],[-120,-8],[0,68],[72.477,5.575],[-2,-80],[-76,0],[2,-128],[0,0],[0,0]],"o":[[-26,50],[120,8],[0,-68],[-72.477,-5.575],[3.652,146.078],[76,0],[-2,128],[0,0],[0,0]],"v":[[-920,-114],[-512,-256],[-334,-454],[-434,-564],[-584,-476],[-402,-332],[-174,-194],[-69.5,-58.25],[59.5,-58.25]],"c":false},"ix":2},"nm":"Path 1","mn":"ADBE Vector Shape - Group","hd":false},{"ty":"st","c":{"a":0,"k":[0.525490196078,0.270588235294,1,1],"ix":3},"o":{"a":0,"k":100,"ix":4},"w":{"a":0,"k":20,"ix":5},"lc":2,"lj":2,"bm":0,"nm":"Stroke 1","mn":"ADBE Vector Graphic - Stroke","hd":false},{"ty":"tr","p":{"a":0,"k":[0,0],"ix":2},"a":{"a":0,"k":[0,0],"ix":1},"s":{"a":0,"k":[100,100],"ix":3},"r":{"a":0,"k":0,"ix":6},"o":{"a":0,"k":100,"ix":7},"sk":{"a":0,"k":0,"ix":4},"sa":{"a":0,"k":0,"ix":5},"nm":"Transform"}],"nm":"Shape 1","np":3,"cix":2,"bm":0,"ix":1,"mn":"ADBE Vector Group","hd":false},{"ty":"tm","s":{"a":1,"k":[{"i":{"x":[0],"y":[1.003]},"o":{"x":[0.167],"y":[0.167]},"t":0,"s":[0]},{"t":60,"s":[100]}],"ix":1},"e":{"a":1,"k":[{"i":{"x":[0.154],"y":[1.003]},"o":{"x":[0.167],"y":[0.167]},"t":0,"s":[0]},{"t":80,"s":[93.7]}],"ix":2},"o":{"a":0,"k":0,"ix":3},"m":1,"ix":2,"nm":"Trim Paths 1","mn":"ADBE Vector Filter - Trim","hd":false}],"ip":0,"op":120,"st":0,"bm":0},{"ddd":0,"ind":28,"ty":4,"nm":"Shape Layer 3","sr":1,"ks":{"o":{"a":0,"k":100,"ix":11},"r":{"a":0,"k":0,"ix":10},"p":{"a":0,"k":[798.269,536.375,0],"ix":2,"l":2},"a":{"a":0,"k":[-1.731,-63.625,0],"ix":1,"l":2},"s":{"a":0,"k":[100,100,100],"ix":6,"l":2}},"ao":0,"shapes":[{"ty":"gr","it":[{"ind":0,"ty":"sh","ix":1,"ks":{"a":0,"k":{"i":[[-174,2],[-6,-86],[45.629,2.444],[2,-134],[-92,-2],[0,0],[-12.249,0.144],[1.5,-19.25],[2.75,-9.25]],"o":[[174,-2],[6,86],[-45.629,-2.444],[-2,134],[22.085,0.48],[0,0],[21.25,-0.25],[-2.118,27.186],[-2.75,9.25]],"v":[[-170,-702],[36,-540],[-124,-452],[-288,-314],[-158,-106],[-66.5,-102.75],[42,-102.75],[62.5,-84],[56.25,-24.5]],"c":false},"ix":2},"nm":"Path 1","mn":"ADBE Vector Shape - Group","hd":false},{"ty":"st","c":{"a":0,"k":[0.525490196078,0.270588235294,1,1],"ix":3},"o":{"a":0,"k":100,"ix":4},"w":{"a":0,"k":20,"ix":5},"lc":2,"lj":2,"bm":0,"nm":"Stroke 1","mn":"ADBE Vector Graphic - Stroke","hd":false},{"ty":"tr","p":{"a":0,"k":[0,0],"ix":2},"a":{"a":0,"k":[0,0],"ix":1},"s":{"a":0,"k":[100,100],"ix":3},"r":{"a":0,"k":0,"ix":6},"o":{"a":0,"k":100,"ix":7},"sk":{"a":0,"k":0,"ix":4},"sa":{"a":0,"k":0,"ix":5},"nm":"Transform"}],"nm":"Shape 1","np":3,"cix":2,"bm":0,"ix":1,"mn":"ADBE Vector Group","hd":false},{"ty":"tm","s":{"a":1,"k":[{"i":{"x":[0],"y":[0.994]},"o":{"x":[0.167],"y":[0.167]},"t":0,"s":[0]},{"t":60,"s":[100]}],"ix":1},"e":{"a":1,"k":[{"i":{"x":[0.158],"y":[0.992]},"o":{"x":[0.167],"y":[0.167]},"t":0,"s":[0]},{"t":80,"s":[84.7]}],"ix":2},"o":{"a":0,"k":0,"ix":3},"m":1,"ix":2,"nm":"Trim Paths 1","mn":"ADBE Vector Filter - Trim","hd":false}],"ip":0,"op":120,"st":0,"bm":0},{"ddd":0,"ind":29,"ty":4,"nm":"Shape Layer 2","sr":1,"ks":{"o":{"a":0,"k":100,"ix":11},"r":{"a":0,"k":0,"ix":10},"p":{"a":0,"k":[573.25,665.25,0],"ix":2,"l":2},"a":{"a":0,"k":[-226.75,65.25,0],"ix":1,"l":2},"s":{"a":0,"k":[100,100,100],"ix":6,"l":2}},"ao":0,"shapes":[{"ty":"gr","it":[{"ind":0,"ty":"sh","ix":1,"ks":{"a":0,"k":{"i":[[-46,-6],[-6,66],[82,4],[10,-94],[-52,0],[28,120],[12,126],[0,0],[0,0]],"o":[[46,6],[6,-66],[-82,-4],[-10,94],[52,0],[-28,-120],[-12,-126],[0,0],[0,0]],"v":[[-552,672],[-362,420],[-506,272],[-658,376],[-486,528],[-316,384],[-450,172],[-321.25,65.25],[-132.25,65.25]],"c":false},"ix":2},"nm":"Path 1","mn":"ADBE Vector Shape - Group","hd":false},{"ty":"st","c":{"a":0,"k":[0.525490196078,0.270588235294,1,1],"ix":3},"o":{"a":0,"k":100,"ix":4},"w":{"a":0,"k":20,"ix":5},"lc":2,"lj":2,"bm":0,"nm":"Stroke 1","mn":"ADBE Vector Graphic - Stroke","hd":false},{"ty":"tr","p":{"a":0,"k":[0,0],"ix":2},"a":{"a":0,"k":[0,0],"ix":1},"s":{"a":0,"k":[100,100],"ix":3},"r":{"a":0,"k":0,"ix":6},"o":{"a":0,"k":100,"ix":7},"sk":{"a":0,"k":0,"ix":4},"sa":{"a":0,"k":0,"ix":5},"nm":"Transform"}],"nm":"Shape 1","np":3,"cix":2,"bm":0,"ix":1,"mn":"ADBE Vector Group","hd":false},{"ty":"tm","s":{"a":1,"k":[{"i":{"x":[0],"y":[0.977]},"o":{"x":[0.167],"y":[0.167]},"t":0,"s":[0]},{"t":60,"s":[100]}],"ix":1},"e":{"a":1,"k":[{"i":{"x":[0.155],"y":[0.971]},"o":{"x":[0.167],"y":[0.167]},"t":0,"s":[0]},{"t":80,"s":[90.1]}],"ix":2},"o":{"a":0,"k":0,"ix":3},"m":1,"ix":2,"nm":"Trim Paths 1","mn":"ADBE Vector Filter - Trim","hd":false}],"ip":0,"op":120,"st":0,"bm":0},{"ddd":0,"ind":30,"ty":4,"nm":"Shape Layer 1","sr":1,"ks":{"o":{"a":0,"k":100,"ix":11},"r":{"a":0,"k":0,"ix":10},"p":{"a":0,"k":[535.75,550.5,0],"ix":2,"l":2},"a":{"a":0,"k":[-264.25,-49.5,0],"ix":1,"l":2},"s":{"a":0,"k":[100,100,100],"ix":6,"l":2}},"ao":0,"shapes":[{"ty":"gr","it":[{"ind":0,"ty":"sh","ix":1,"ks":{"a":0,"k":{"i":[[2,210],[-34,-58],[46,-30],[10,-54],[-96,-8],[-86,90],[0,0],[0,0],[0,17.5],[0,0],[0,0],[-10.407,-11.223],[0,0]],"o":[[-2,-210],[34,58],[-46,30],[-10,54],[96,8],[86,-90],[0,0],[0,0],[0,-17.5],[0,0],[0,0],[12.75,13.75],[0,0]],"v":[[-894,-246],[-632,-290],[-640,-124],[-760,18],[-688,206],[-480,92],[-303.75,-1],[-247,-35],[-227,-70.25],[-227.5,-95.25],[-227,-65.25],[-211,-39.75],[-152.25,-1.75]],"c":false},"ix":2},"nm":"Path 1","mn":"ADBE Vector Shape - Group","hd":false},{"ty":"st","c":{"a":0,"k":[0.525490196078,0.270588235294,1,1],"ix":3},"o":{"a":0,"k":100,"ix":4},"w":{"a":0,"k":20,"ix":5},"lc":2,"lj":2,"bm":0,"nm":"Stroke 1","mn":"ADBE Vector Graphic - Stroke","hd":false},{"ty":"tr","p":{"a":0,"k":[0,0],"ix":2},"a":{"a":0,"k":[0,0],"ix":1},"s":{"a":0,"k":[100,100],"ix":3},"r":{"a":0,"k":0,"ix":6},"o":{"a":0,"k":100,"ix":7},"sk":{"a":0,"k":0,"ix":4},"sa":{"a":0,"k":0,"ix":5},"nm":"Transform"}],"nm":"Shape 1","np":3,"cix":2,"bm":0,"ix":1,"mn":"ADBE Vector Group","hd":false},{"ty":"tm","s":{"a":1,"k":[{"i":{"x":[0],"y":[0.988]},"o":{"x":[0.167],"y":[0.167]},"t":0,"s":[0]},{"t":60,"s":[100]}],"ix":1},"e":{"a":1,"k":[{"i":{"x":[0.154],"y":[0.984]},"o":{"x":[0.167],"y":[0.167]},"t":0,"s":[0]},{"t":80,"s":[84.4]}],"ix":2},"o":{"a":0,"k":0,"ix":3},"m":1,"ix":2,"nm":"Trim Paths 1","mn":"ADBE Vector Filter - Trim","hd":false}],"ip":0,"op":120,"st":0,"bm":0}]}],"layers":[{"ddd":0,"ind":1,"ty":0,"nm":"schoolbook","refId":"comp_0","sr":1,"ks":{"o":{"a":1,"k":[{"i":{"x":[0.833],"y":[0.833]},"o":{"x":[0.167],"y":[0.167]},"t":90,"s":[100]},{"t":119,"s":[0]}],"ix":11},"r":{"a":0,"k":0,"ix":10},"p":{"a":0,"k":[800,600,0],"ix":2,"l":2},"a":{"a":0,"k":[800,600,0],"ix":1,"l":2},"s":{"a":0,"k":[100,100,100],"ix":6,"l":2}},"ao":0,"w":1600,"h":1200,"ip":0,"op":120,"st":0,"bm":0}],"markers":[]}